{
  "nightly": {
    "description": "Unstable",
    "hide": false,
    "last_updated": "2025-04-02T10:20:48.000Z",
    "last_updated_url": "https://github.com/hotio/jellyfin/actions/runs/14217023703",
    "latest": false,
    "tags": [
      "nightly",
      "nightly-2025033105",
      "nightly-eb0abf5"
    ]
  },
  "release": {
    "description": "Stable",
    "hide": false,
    "last_updated": "2025-04-02T10:20:47.000Z",
    "last_updated_url": "https://github.com/hotio/jellyfin/actions/runs/14217035109",
    "latest": true,
    "tags": [
      "release",
      "release-10.10.6",
      "release-be73ac1"
    ]
  }
}
