{
  "nightly": {
    "description": "Unstable",
    "hide": false,
    "last_updated": "2025-10-27T05:45:42.000Z",
    "last_updated_url": "https://github.com/hotio/jellyfin/actions/runs/18830970523",
    "latest": false,
    "tags": [
      "nightly",
      "nightly-2025102705",
      "nightly-c8ce8b0"
    ]
  },
  "release": {
    "description": "Stable",
    "hide": false,
    "last_updated": "2025-10-27T02:59:40.000Z",
    "last_updated_url": "https://github.com/hotio/jellyfin/actions/runs/18828198331",
    "latest": true,
    "tags": [
      "release",
      "release-10.11.1",
      "release-6695b47"
    ]
  }
}
